<?xml version="1.0" encoding="UTF-8" standalone="yes"?>
<p:sld xmlns:a="http://schemas.openxmlformats.org/drawingml/2006/main" xmlns:r="http://schemas.openxmlformats.org/officeDocument/2006/relationships" xmlns:p="http://schemas.openxmlformats.org/presentationml/2006/main"><p:cSld><p:spTree><p:nvGrpSpPr><p:cNvPr id="1" name=""/><p:cNvGrpSpPr/><p:nvPr/></p:nvGrpSpPr><p:grpSpPr><a:xfrm><a:off x="0" y="0"/><a:ext cx="0" cy="0"/><a:chOff x="0" y="0"/><a:chExt cx="0" cy="0"/></a:xfrm></p:grpSpPr><p:sp><p:nvSpPr><p:cNvPr id="2" name="Title 1"/><p:cNvSpPr><a:spLocks noGrp="1"/></p:cNvSpPr><p:nvPr><p:ph type="title"/></p:nvPr></p:nvSpPr><p:spPr><a:xfrm><a:off x="777249" y="89620"/><a:ext cx="7968975" cy="1143000"/></a:xfrm></p:spPr><p:txBody><a:bodyPr><a:normAutofit fontScale="90000"/></a:bodyPr><a:lstStyle/><a:p><a:r><a:rPr lang="en-US" dirty="0" smtClean="0"/><a:t>Current State:</a:t></a:r><a:br><a:rPr lang="en-US" dirty="0" smtClean="0"/></a:br><a:r><a:rPr lang="en-US" dirty="0" smtClean="0"/><a:t> Demographic Analysis Panel</a:t></a:r><a:endParaRPr lang="en-US" dirty="0"/></a:p></p:txBody></p:sp><p:sp><p:nvSpPr><p:cNvPr id="7" name="Freeform 6"/><p:cNvSpPr/><p:nvPr/></p:nvSpPr><p:spPr><a:xfrm><a:off x="1687990" y="1742809"/><a:ext cx="1040182" cy="1003136"/></a:xfrm><a:custGeom><a:avLst/><a:gdLst><a:gd name="connsiteX0" fmla="*/ 0 w 1486621"/><a:gd name="connsiteY0" fmla="*/ 93378 h 933784"/><a:gd name="connsiteX1" fmla="*/ 27350 w 1486621"/><a:gd name="connsiteY1" fmla="*/ 27350 h 933784"/><a:gd name="connsiteX2" fmla="*/ 93378 w 1486621"/><a:gd name="connsiteY2" fmla="*/ 0 h 933784"/><a:gd name="connsiteX3" fmla="*/ 1393243 w 1486621"/><a:gd name="connsiteY3" fmla="*/ 0 h 933784"/><a:gd name="connsiteX4" fmla="*/ 1459271 w 1486621"/><a:gd name="connsiteY4" fmla="*/ 27350 h 933784"/><a:gd name="connsiteX5" fmla="*/ 1486621 w 1486621"/><a:gd name="connsiteY5" fmla="*/ 93378 h 933784"/><a:gd name="connsiteX6" fmla="*/ 1486621 w 1486621"/><a:gd name="connsiteY6" fmla="*/ 840406 h 933784"/><a:gd name="connsiteX7" fmla="*/ 1459271 w 1486621"/><a:gd name="connsiteY7" fmla="*/ 906434 h 933784"/><a:gd name="connsiteX8" fmla="*/ 1393243 w 1486621"/><a:gd name="connsiteY8" fmla="*/ 933784 h 933784"/><a:gd name="connsiteX9" fmla="*/ 93378 w 1486621"/><a:gd name="connsiteY9" fmla="*/ 933784 h 933784"/><a:gd name="connsiteX10" fmla="*/ 27350 w 1486621"/><a:gd name="connsiteY10" fmla="*/ 906434 h 933784"/><a:gd name="connsiteX11" fmla="*/ 0 w 1486621"/><a:gd name="connsiteY11" fmla="*/ 840406 h 933784"/><a:gd name="connsiteX12" fmla="*/ 0 w 1486621"/><a:gd name="connsiteY12" fmla="*/ 93378 h 933784"/></a:gdLst><a:ahLst/><a:cxnLst><a:cxn ang="0"><a:pos x="connsiteX0" y="connsiteY0"/></a:cxn><a:cxn ang="0"><a:pos x="connsiteX1" y="connsiteY1"/></a:cxn><a:cxn ang="0"><a:pos x="connsiteX2" y="connsiteY2"/></a:cxn><a:cxn ang="0"><a:pos x="connsiteX3" y="connsiteY3"/></a:cxn><a:cxn ang="0"><a:pos x="connsiteX4" y="connsiteY4"/></a:cxn><a:cxn ang="0"><a:pos x="connsiteX5" y="connsiteY5"/></a:cxn><a:cxn ang="0"><a:pos x="connsiteX6" y="connsiteY6"/></a:cxn><a:cxn ang="0"><a:pos x="connsiteX7" y="connsiteY7"/></a:cxn><a:cxn ang="0"><a:pos x="connsiteX8" y="connsiteY8"/></a:cxn><a:cxn ang="0"><a:pos x="connsiteX9" y="connsiteY9"/></a:cxn><a:cxn ang="0"><a:pos x="connsiteX10" y="connsiteY10"/></a:cxn><a:cxn ang="0"><a:pos x="connsiteX11" y="connsiteY11"/></a:cxn><a:cxn ang="0"><a:pos x="connsiteX12" y="connsiteY12"/></a:cxn></a:cxnLst><a:rect l="l" t="t" r="r" b="b"/><a:pathLst><a:path w="1486621" h="933784"><a:moveTo><a:pt x="0" y="93378"/></a:moveTo><a:cubicBezTo><a:pt x="0" y="68613"/><a:pt x="9838" y="44862"/><a:pt x="27350" y="27350"/></a:cubicBezTo><a:cubicBezTo><a:pt x="44862" y="9838"/><a:pt x="68613" y="0"/><a:pt x="93378" y="0"/></a:cubicBezTo><a:lnTo><a:pt x="1393243" y="0"/></a:lnTo><a:cubicBezTo><a:pt x="1418008" y="0"/><a:pt x="1441759" y="9838"/><a:pt x="1459271" y="27350"/></a:cubicBezTo><a:cubicBezTo><a:pt x="1476783" y="44862"/><a:pt x="1486621" y="68613"/><a:pt x="1486621" y="93378"/></a:cubicBezTo><a:lnTo><a:pt x="1486621" y="840406"/></a:lnTo><a:cubicBezTo><a:pt x="1486621" y="865171"/><a:pt x="1476783" y="888922"/><a:pt x="1459271" y="906434"/></a:cubicBezTo><a:cubicBezTo><a:pt x="1441759" y="923946"/><a:pt x="1418008" y="933784"/><a:pt x="1393243" y="933784"/></a:cubicBezTo><a:lnTo><a:pt x="93378" y="933784"/></a:lnTo><a:cubicBezTo><a:pt x="68613" y="933784"/><a:pt x="44862" y="923946"/><a:pt x="27350" y="906434"/></a:cubicBezTo><a:cubicBezTo><a:pt x="9838" y="888922"/><a:pt x="0" y="865171"/><a:pt x="0" y="840406"/></a:cubicBezTo><a:lnTo><a:pt x="0" y="93378"/></a:lnTo><a:close/></a:path></a:pathLst></a:custGeom><a:solidFill><a:srgbClr val="CCECFF"/></a:solidFill></p:spPr><p:style><a:lnRef idx="2"><a:schemeClr val="lt1"><a:hueOff val="0"/><a:satOff val="0"/><a:lumOff val="0"/><a:alphaOff val="0"/></a:schemeClr></a:lnRef><a:fillRef idx="1"><a:scrgbClr r="0" g="0" b="0"/></a:fillRef><a:effectRef idx="0"><a:schemeClr val="accent2"><a:hueOff val="0"/><a:satOff val="0"/><a:lumOff val="0"/><a:alphaOff val="0"/></a:schemeClr></a:effectRef><a:fontRef idx="minor"><a:schemeClr val="lt1"/></a:fontRef></p:style><p:txBody><a:bodyPr spcFirstLastPara="0" vert="horz" wrap="square" lIns="95930" tIns="95930" rIns="95930" bIns="95930" numCol="1" spcCol="1270" anchor="ctr" anchorCtr="0"><a:noAutofit/></a:bodyPr><a:lstStyle/><a:p><a:pPr lvl="0" algn="ctr" defTabSz="800100"><a:lnSpc><a:spcPct val="90000"/></a:lnSpc><a:spcBef><a:spcPct val="0"/></a:spcBef><a:spcAft><a:spcPct val="35000"/></a:spcAft></a:pPr><a:r><a:rPr lang="en-US" sz="1600" dirty="0" smtClean="0"><a:solidFill><a:schemeClr val="tx1"/></a:solidFill></a:rPr><a:t>Observed</a:t></a:r><a:r><a:rPr lang="en-US" sz="1600" kern="1200" baseline="0" dirty="0" smtClean="0"><a:solidFill><a:schemeClr val="tx1"/></a:solidFill></a:rPr><a:t> Datasets</a:t></a:r></a:p></p:txBody></p:sp><p:sp><p:nvSpPr><p:cNvPr id="8" name="Freeform 7"/><p:cNvSpPr/><p:nvPr/></p:nvSpPr><p:spPr><a:xfrm><a:off x="3129995" y="1836937"/><a:ext cx="473966" cy="814882"/></a:xfrm><a:custGeom><a:avLst/><a:gdLst><a:gd name="connsiteX0" fmla="*/ 0 w 528044"/><a:gd name="connsiteY0" fmla="*/ 151709 h 758545"/><a:gd name="connsiteX1" fmla="*/ 264022 w 528044"/><a:gd name="connsiteY1" fmla="*/ 151709 h 758545"/><a:gd name="connsiteX2" fmla="*/ 264022 w 528044"/><a:gd name="connsiteY2" fmla="*/ 0 h 758545"/><a:gd name="connsiteX3" fmla="*/ 528044 w 528044"/><a:gd name="connsiteY3" fmla="*/ 379273 h 758545"/><a:gd name="connsiteX4" fmla="*/ 264022 w 528044"/><a:gd name="connsiteY4" fmla="*/ 758545 h 758545"/><a:gd name="connsiteX5" fmla="*/ 264022 w 528044"/><a:gd name="connsiteY5" fmla="*/ 606836 h 758545"/><a:gd name="connsiteX6" fmla="*/ 0 w 528044"/><a:gd name="connsiteY6" fmla="*/ 606836 h 758545"/><a:gd name="connsiteX7" fmla="*/ 0 w 528044"/><a:gd name="connsiteY7" fmla="*/ 151709 h 758545"/></a:gdLst><a:ahLst/><a:cxnLst><a:cxn ang="0"><a:pos x="connsiteX0" y="connsiteY0"/></a:cxn><a:cxn ang="0"><a:pos x="connsiteX1" y="connsiteY1"/></a:cxn><a:cxn ang="0"><a:pos x="connsiteX2" y="connsiteY2"/></a:cxn><a:cxn ang="0"><a:pos x="connsiteX3" y="connsiteY3"/></a:cxn><a:cxn ang="0"><a:pos x="connsiteX4" y="connsiteY4"/></a:cxn><a:cxn ang="0"><a:pos x="connsiteX5" y="connsiteY5"/></a:cxn><a:cxn ang="0"><a:pos x="connsiteX6" y="connsiteY6"/></a:cxn><a:cxn ang="0"><a:pos x="connsiteX7" y="connsiteY7"/></a:cxn></a:cxnLst><a:rect l="l" t="t" r="r" b="b"/><a:pathLst><a:path w="528044" h="758545"><a:moveTo><a:pt x="0" y="151709"/></a:moveTo><a:lnTo><a:pt x="264022" y="151709"/></a:lnTo><a:lnTo><a:pt x="264022" y="0"/></a:lnTo><a:lnTo><a:pt x="528044" y="379273"/></a:lnTo><a:lnTo><a:pt x="264022" y="758545"/></a:lnTo><a:lnTo><a:pt x="264022" y="606836"/></a:lnTo><a:lnTo><a:pt x="0" y="606836"/></a:lnTo><a:lnTo><a:pt x="0" y="151709"/></a:lnTo><a:close/></a:path></a:pathLst></a:custGeom></p:spPr><p:style><a:lnRef idx="0"><a:schemeClr val="accent2"><a:tint val="60000"/><a:hueOff val="0"/><a:satOff val="0"/><a:lumOff val="0"/><a:alphaOff val="0"/></a:schemeClr></a:lnRef><a:fillRef idx="1"><a:schemeClr val="accent2"><a:tint val="60000"/><a:hueOff val="0"/><a:satOff val="0"/><a:lumOff val="0"/><a:alphaOff val="0"/></a:schemeClr></a:fillRef><a:effectRef idx="0"><a:schemeClr val="accent2"><a:tint val="60000"/><a:hueOff val="0"/><a:satOff val="0"/><a:lumOff val="0"/><a:alphaOff val="0"/></a:schemeClr></a:effectRef><a:fontRef idx="minor"><a:schemeClr val="lt1"/></a:fontRef></p:style><p:txBody><a:bodyPr spcFirstLastPara="0" vert="horz" wrap="square" lIns="0" tIns="151709" rIns="158413" bIns="151709" numCol="1" spcCol="1270" anchor="ctr" anchorCtr="0"><a:noAutofit/></a:bodyPr><a:lstStyle/><a:p><a:pPr lvl="0" algn="ctr" defTabSz="622300"><a:lnSpc><a:spcPct val="90000"/></a:lnSpc><a:spcAft><a:spcPct val="35000"/></a:spcAft></a:pPr><a:r><a:rPr lang="en-US" sz="900" dirty="0"><a:solidFill><a:schemeClr val="tx1"/></a:solidFill></a:rPr><a:t>CODE</a:t></a:r><a:endParaRPr lang="en-US" sz="1000" kern="1200" dirty="0"><a:solidFill><a:schemeClr val="tx1"/></a:solidFill></a:endParaRPr></a:p></p:txBody></p:sp><p:sp><p:nvSpPr><p:cNvPr id="9" name="Freeform 8"/><p:cNvSpPr/><p:nvPr/></p:nvSpPr><p:spPr><a:xfrm><a:off x="4008983" y="1742809"/><a:ext cx="980478" cy="1003136"/></a:xfrm><a:custGeom><a:avLst/><a:gdLst><a:gd name="connsiteX0" fmla="*/ 0 w 1486621"/><a:gd name="connsiteY0" fmla="*/ 93378 h 933784"/><a:gd name="connsiteX1" fmla="*/ 27350 w 1486621"/><a:gd name="connsiteY1" fmla="*/ 27350 h 933784"/><a:gd name="connsiteX2" fmla="*/ 93378 w 1486621"/><a:gd name="connsiteY2" fmla="*/ 0 h 933784"/><a:gd name="connsiteX3" fmla="*/ 1393243 w 1486621"/><a:gd name="connsiteY3" fmla="*/ 0 h 933784"/><a:gd name="connsiteX4" fmla="*/ 1459271 w 1486621"/><a:gd name="connsiteY4" fmla="*/ 27350 h 933784"/><a:gd name="connsiteX5" fmla="*/ 1486621 w 1486621"/><a:gd name="connsiteY5" fmla="*/ 93378 h 933784"/><a:gd name="connsiteX6" fmla="*/ 1486621 w 1486621"/><a:gd name="connsiteY6" fmla="*/ 840406 h 933784"/><a:gd name="connsiteX7" fmla="*/ 1459271 w 1486621"/><a:gd name="connsiteY7" fmla="*/ 906434 h 933784"/><a:gd name="connsiteX8" fmla="*/ 1393243 w 1486621"/><a:gd name="connsiteY8" fmla="*/ 933784 h 933784"/><a:gd name="connsiteX9" fmla="*/ 93378 w 1486621"/><a:gd name="connsiteY9" fmla="*/ 933784 h 933784"/><a:gd name="connsiteX10" fmla="*/ 27350 w 1486621"/><a:gd name="connsiteY10" fmla="*/ 906434 h 933784"/><a:gd name="connsiteX11" fmla="*/ 0 w 1486621"/><a:gd name="connsiteY11" fmla="*/ 840406 h 933784"/><a:gd name="connsiteX12" fmla="*/ 0 w 1486621"/><a:gd name="connsiteY12" fmla="*/ 93378 h 933784"/></a:gdLst><a:ahLst/><a:cxnLst><a:cxn ang="0"><a:pos x="connsiteX0" y="connsiteY0"/></a:cxn><a:cxn ang="0"><a:pos x="connsiteX1" y="connsiteY1"/></a:cxn><a:cxn ang="0"><a:pos x="connsiteX2" y="connsiteY2"/></a:cxn><a:cxn ang="0"><a:pos x="connsiteX3" y="connsiteY3"/></a:cxn><a:cxn ang="0"><a:pos x="connsiteX4" y="connsiteY4"/></a:cxn><a:cxn ang="0"><a:pos x="connsiteX5" y="connsiteY5"/></a:cxn><a:cxn ang="0"><a:pos x="connsiteX6" y="connsiteY6"/></a:cxn><a:cxn ang="0"><a:pos x="connsiteX7" y="connsiteY7"/></a:cxn><a:cxn ang="0"><a:pos x="connsiteX8" y="connsiteY8"/></a:cxn><a:cxn ang="0"><a:pos x="connsiteX9" y="connsiteY9"/></a:cxn><a:cxn ang="0"><a:pos x="connsiteX10" y="connsiteY10"/></a:cxn><a:cxn ang="0"><a:pos x="connsiteX11" y="connsiteY11"/></a:cxn><a:cxn ang="0"><a:pos x="connsiteX12" y="connsiteY12"/></a:cxn></a:cxnLst><a:rect l="l" t="t" r="r" b="b"/><a:pathLst><a:path w="1486621" h="933784"><a:moveTo><a:pt x="0" y="93378"/></a:moveTo><a:cubicBezTo><a:pt x="0" y="68613"/><a:pt x="9838" y="44862"/><a:pt x="27350" y="27350"/></a:cubicBezTo><a:cubicBezTo><a:pt x="44862" y="9838"/><a:pt x="68613" y="0"/><a:pt x="93378" y="0"/></a:cubicBezTo><a:lnTo><a:pt x="1393243" y="0"/></a:lnTo><a:cubicBezTo><a:pt x="1418008" y="0"/><a:pt x="1441759" y="9838"/><a:pt x="1459271" y="27350"/></a:cubicBezTo><a:cubicBezTo><a:pt x="1476783" y="44862"/><a:pt x="1486621" y="68613"/><a:pt x="1486621" y="93378"/></a:cubicBezTo><a:lnTo><a:pt x="1486621" y="840406"/></a:lnTo><a:cubicBezTo><a:pt x="1486621" y="865171"/><a:pt x="1476783" y="888922"/><a:pt x="1459271" y="906434"/></a:cubicBezTo><a:cubicBezTo><a:pt x="1441759" y="923946"/><a:pt x="1418008" y="933784"/><a:pt x="1393243" y="933784"/></a:cubicBezTo><a:lnTo><a:pt x="93378" y="933784"/></a:lnTo><a:cubicBezTo><a:pt x="68613" y="933784"/><a:pt x="44862" y="923946"/><a:pt x="27350" y="906434"/></a:cubicBezTo><a:cubicBezTo><a:pt x="9838" y="888922"/><a:pt x="0" y="865171"/><a:pt x="0" y="840406"/></a:cubicBezTo><a:lnTo><a:pt x="0" y="93378"/></a:lnTo><a:close/></a:path></a:pathLst></a:custGeom><a:solidFill><a:srgbClr val="CCECFF"/></a:solidFill><a:ln><a:solidFill><a:srgbClr val="CCECFF"/></a:solidFill></a:ln></p:spPr><p:style><a:lnRef idx="2"><a:scrgbClr r="0" g="0" b="0"/></a:lnRef><a:fillRef idx="1"><a:scrgbClr r="0" g="0" b="0"/></a:fillRef><a:effectRef idx="0"><a:schemeClr val="accent2"><a:hueOff val="0"/><a:satOff val="0"/><a:lumOff val="0"/><a:alphaOff val="0"/></a:schemeClr></a:effectRef><a:fontRef idx="minor"><a:schemeClr val="lt1"/></a:fontRef></p:style><p:txBody><a:bodyPr spcFirstLastPara="0" vert="horz" wrap="square" lIns="95930" tIns="95930" rIns="95930" bIns="95930" numCol="1" spcCol="1270" anchor="ctr" anchorCtr="0"><a:noAutofit/></a:bodyPr><a:lstStyle/><a:p><a:pPr lvl="0" algn="ctr" defTabSz="800100"><a:lnSpc><a:spcPct val="90000"/></a:lnSpc><a:spcBef><a:spcPct val="0"/></a:spcBef><a:spcAft><a:spcPct val="35000"/></a:spcAft></a:pPr><a:r><a:rPr lang="en-US" sz="1600" kern="1200" dirty="0" smtClean="0"><a:solidFill><a:schemeClr val="tx1"/></a:solidFill></a:rPr><a:t>Analysis Datasets</a:t></a:r><a:endParaRPr lang="en-US" sz="1600" kern="1200" dirty="0"><a:solidFill><a:schemeClr val="tx1"/></a:solidFill></a:endParaRPr></a:p></p:txBody></p:sp><p:sp><p:nvSpPr><p:cNvPr id="10" name="Freeform 9"/><p:cNvSpPr/><p:nvPr/></p:nvSpPr><p:spPr><a:xfrm><a:off x="5427937" y="1836937"/><a:ext cx="510173" cy="814882"/></a:xfrm><a:custGeom><a:avLst/><a:gdLst><a:gd name="connsiteX0" fmla="*/ 0 w 517155"/><a:gd name="connsiteY0" fmla="*/ 151709 h 758545"/><a:gd name="connsiteX1" fmla="*/ 258578 w 517155"/><a:gd name="connsiteY1" fmla="*/ 151709 h 758545"/><a:gd name="connsiteX2" fmla="*/ 258578 w 517155"/><a:gd name="connsiteY2" fmla="*/ 0 h 758545"/><a:gd name="connsiteX3" fmla="*/ 517155 w 517155"/><a:gd name="connsiteY3" fmla="*/ 379273 h 758545"/><a:gd name="connsiteX4" fmla="*/ 258578 w 517155"/><a:gd name="connsiteY4" fmla="*/ 758545 h 758545"/><a:gd name="connsiteX5" fmla="*/ 258578 w 517155"/><a:gd name="connsiteY5" fmla="*/ 606836 h 758545"/><a:gd name="connsiteX6" fmla="*/ 0 w 517155"/><a:gd name="connsiteY6" fmla="*/ 606836 h 758545"/><a:gd name="connsiteX7" fmla="*/ 0 w 517155"/><a:gd name="connsiteY7" fmla="*/ 151709 h 758545"/></a:gdLst><a:ahLst/><a:cxnLst><a:cxn ang="0"><a:pos x="connsiteX0" y="connsiteY0"/></a:cxn><a:cxn ang="0"><a:pos x="connsiteX1" y="connsiteY1"/></a:cxn><a:cxn ang="0"><a:pos x="connsiteX2" y="connsiteY2"/></a:cxn><a:cxn ang="0"><a:pos x="connsiteX3" y="connsiteY3"/></a:cxn><a:cxn ang="0"><a:pos x="connsiteX4" y="connsiteY4"/></a:cxn><a:cxn ang="0"><a:pos x="connsiteX5" y="connsiteY5"/></a:cxn><a:cxn ang="0"><a:pos x="connsiteX6" y="connsiteY6"/></a:cxn><a:cxn ang="0"><a:pos x="connsiteX7" y="connsiteY7"/></a:cxn></a:cxnLst><a:rect l="l" t="t" r="r" b="b"/><a:pathLst><a:path w="517155" h="758545"><a:moveTo><a:pt x="0" y="151709"/></a:moveTo><a:lnTo><a:pt x="258578" y="151709"/></a:lnTo><a:lnTo><a:pt x="258578" y="0"/></a:lnTo><a:lnTo><a:pt x="517155" y="379273"/></a:lnTo><a:lnTo><a:pt x="258578" y="758545"/></a:lnTo><a:lnTo><a:pt x="258578" y="606836"/></a:lnTo><a:lnTo><a:pt x="0" y="606836"/></a:lnTo><a:lnTo><a:pt x="0" y="151709"/></a:lnTo><a:close/></a:path></a:pathLst></a:custGeom></p:spPr><p:style><a:lnRef idx="0"><a:schemeClr val="accent2"><a:tint val="60000"/><a:hueOff val="0"/><a:satOff val="0"/><a:lumOff val="0"/><a:alphaOff val="0"/></a:schemeClr></a:lnRef><a:fillRef idx="1"><a:schemeClr val="accent2"><a:tint val="60000"/><a:hueOff val="0"/><a:satOff val="0"/><a:lumOff val="0"/><a:alphaOff val="0"/></a:schemeClr></a:fillRef><a:effectRef idx="0"><a:schemeClr val="accent2"><a:tint val="60000"/><a:hueOff val="0"/><a:satOff val="0"/><a:lumOff val="0"/><a:alphaOff val="0"/></a:schemeClr></a:effectRef><a:fontRef idx="minor"><a:schemeClr val="lt1"/></a:fontRef></p:style><p:txBody><a:bodyPr spcFirstLastPara="0" vert="horz" wrap="square" lIns="0" tIns="151709" rIns="155146" bIns="151709" numCol="1" spcCol="1270" anchor="ctr" anchorCtr="0"><a:noAutofit/></a:bodyPr><a:lstStyle/><a:p><a:pPr lvl="0" algn="ctr" defTabSz="622300"><a:lnSpc><a:spcPct val="90000"/></a:lnSpc><a:spcAft><a:spcPct val="35000"/></a:spcAft></a:pPr><a:r><a:rPr lang="en-US" sz="900" dirty="0"><a:solidFill><a:schemeClr val="tx1"/></a:solidFill></a:rPr><a:t>CODE</a:t></a:r><a:endParaRPr lang="en-US" sz="900" kern="1200" dirty="0"><a:solidFill><a:schemeClr val="tx1"/></a:solidFill></a:endParaRPr></a:p></p:txBody></p:sp><p:sp><p:nvSpPr><p:cNvPr id="11" name="Freeform 10"/><p:cNvSpPr/><p:nvPr/></p:nvSpPr><p:spPr><a:xfrm><a:off x="6333090" y="1742809"/><a:ext cx="971130" cy="1003136"/></a:xfrm><a:custGeom><a:avLst/><a:gdLst><a:gd name="connsiteX0" fmla="*/ 0 w 1486621"/><a:gd name="connsiteY0" fmla="*/ 93378 h 933784"/><a:gd name="connsiteX1" fmla="*/ 27350 w 1486621"/><a:gd name="connsiteY1" fmla="*/ 27350 h 933784"/><a:gd name="connsiteX2" fmla="*/ 93378 w 1486621"/><a:gd name="connsiteY2" fmla="*/ 0 h 933784"/><a:gd name="connsiteX3" fmla="*/ 1393243 w 1486621"/><a:gd name="connsiteY3" fmla="*/ 0 h 933784"/><a:gd name="connsiteX4" fmla="*/ 1459271 w 1486621"/><a:gd name="connsiteY4" fmla="*/ 27350 h 933784"/><a:gd name="connsiteX5" fmla="*/ 1486621 w 1486621"/><a:gd name="connsiteY5" fmla="*/ 93378 h 933784"/><a:gd name="connsiteX6" fmla="*/ 1486621 w 1486621"/><a:gd name="connsiteY6" fmla="*/ 840406 h 933784"/><a:gd name="connsiteX7" fmla="*/ 1459271 w 1486621"/><a:gd name="connsiteY7" fmla="*/ 906434 h 933784"/><a:gd name="connsiteX8" fmla="*/ 1393243 w 1486621"/><a:gd name="connsiteY8" fmla="*/ 933784 h 933784"/><a:gd name="connsiteX9" fmla="*/ 93378 w 1486621"/><a:gd name="connsiteY9" fmla="*/ 933784 h 933784"/><a:gd name="connsiteX10" fmla="*/ 27350 w 1486621"/><a:gd name="connsiteY10" fmla="*/ 906434 h 933784"/><a:gd name="connsiteX11" fmla="*/ 0 w 1486621"/><a:gd name="connsiteY11" fmla="*/ 840406 h 933784"/><a:gd name="connsiteX12" fmla="*/ 0 w 1486621"/><a:gd name="connsiteY12" fmla="*/ 93378 h 933784"/></a:gdLst><a:ahLst/><a:cxnLst><a:cxn ang="0"><a:pos x="connsiteX0" y="connsiteY0"/></a:cxn><a:cxn ang="0"><a:pos x="connsiteX1" y="connsiteY1"/></a:cxn><a:cxn ang="0"><a:pos x="connsiteX2" y="connsiteY2"/></a:cxn><a:cxn ang="0"><a:pos x="connsiteX3" y="connsiteY3"/></a:cxn><a:cxn ang="0"><a:pos x="connsiteX4" y="connsiteY4"/></a:cxn><a:cxn ang="0"><a:pos x="connsiteX5" y="connsiteY5"/></a:cxn><a:cxn ang="0"><a:pos x="connsiteX6" y="connsiteY6"/></a:cxn><a:cxn ang="0"><a:pos x="connsiteX7" y="connsiteY7"/></a:cxn><a:cxn ang="0"><a:pos x="connsiteX8" y="connsiteY8"/></a:cxn><a:cxn ang="0"><a:pos x="connsiteX9" y="connsiteY9"/></a:cxn><a:cxn ang="0"><a:pos x="connsiteX10" y="connsiteY10"/></a:cxn><a:cxn ang="0"><a:pos x="connsiteX11" y="connsiteY11"/></a:cxn><a:cxn ang="0"><a:pos x="connsiteX12" y="connsiteY12"/></a:cxn></a:cxnLst><a:rect l="l" t="t" r="r" b="b"/><a:pathLst><a:path w="1486621" h="933784"><a:moveTo><a:pt x="0" y="93378"/></a:moveTo><a:cubicBezTo><a:pt x="0" y="68613"/><a:pt x="9838" y="44862"/><a:pt x="27350" y="27350"/></a:cubicBezTo><a:cubicBezTo><a:pt x="44862" y="9838"/><a:pt x="68613" y="0"/><a:pt x="93378" y="0"/></a:cubicBezTo><a:lnTo><a:pt x="1393243" y="0"/></a:lnTo><a:cubicBezTo><a:pt x="1418008" y="0"/><a:pt x="1441759" y="9838"/><a:pt x="1459271" y="27350"/></a:cubicBezTo><a:cubicBezTo><a:pt x="1476783" y="44862"/><a:pt x="1486621" y="68613"/><a:pt x="1486621" y="93378"/></a:cubicBezTo><a:lnTo><a:pt x="1486621" y="840406"/></a:lnTo><a:cubicBezTo><a:pt x="1486621" y="865171"/><a:pt x="1476783" y="888922"/><a:pt x="1459271" y="906434"/></a:cubicBezTo><a:cubicBezTo><a:pt x="1441759" y="923946"/><a:pt x="1418008" y="933784"/><a:pt x="1393243" y="933784"/></a:cubicBezTo><a:lnTo><a:pt x="93378" y="933784"/></a:lnTo><a:cubicBezTo><a:pt x="68613" y="933784"/><a:pt x="44862" y="923946"/><a:pt x="27350" y="906434"/></a:cubicBezTo><a:cubicBezTo><a:pt x="9838" y="888922"/><a:pt x="0" y="865171"/><a:pt x="0" y="840406"/></a:cubicBezTo><a:lnTo><a:pt x="0" y="93378"/></a:lnTo><a:close/></a:path></a:pathLst></a:custGeom><a:solidFill><a:srgbClr val="CCECFF"/></a:solidFill></p:spPr><p:style><a:lnRef idx="2"><a:schemeClr val="lt1"><a:hueOff val="0"/><a:satOff val="0"/><a:lumOff val="0"/><a:alphaOff val="0"/></a:schemeClr></a:lnRef><a:fillRef idx="1"><a:scrgbClr r="0" g="0" b="0"/></a:fillRef><a:effectRef idx="0"><a:schemeClr val="accent2"><a:hueOff val="0"/><a:satOff val="0"/><a:lumOff val="0"/><a:alphaOff val="0"/></a:schemeClr></a:effectRef><a:fontRef idx="minor"><a:schemeClr val="lt1"/></a:fontRef></p:style><p:txBody><a:bodyPr spcFirstLastPara="0" vert="horz" wrap="square" lIns="95930" tIns="95930" rIns="95930" bIns="95930" numCol="1" spcCol="1270" anchor="ctr" anchorCtr="0"><a:noAutofit/></a:bodyPr><a:lstStyle/><a:p><a:pPr lvl="0" algn="ctr" defTabSz="800100"><a:lnSpc><a:spcPct val="90000"/></a:lnSpc><a:spcBef><a:spcPct val="0"/></a:spcBef><a:spcAft><a:spcPct val="35000"/></a:spcAft></a:pPr><a:r><a:rPr lang="en-US" sz="1600" kern="1200" dirty="0" smtClean="0"><a:solidFill><a:schemeClr val="tx1"/></a:solidFill></a:rPr><a:t>Tables, Figures and Listings</a:t></a:r><a:endParaRPr lang="en-US" sz="1600" kern="1200" dirty="0"><a:solidFill><a:schemeClr val="tx1"/></a:solidFill></a:endParaRPr></a:p></p:txBody></p:sp><p:sp><p:nvSpPr><p:cNvPr id="12" name="TextBox 11"/><p:cNvSpPr txBox="1"/><p:nvPr/></p:nvSpPr><p:spPr><a:xfrm><a:off x="18300" y="1686027"/><a:ext cx="1046860" cy="1077218"/></a:xfrm><a:prstGeom prst="rect"><a:avLst/></a:prstGeom><a:noFill/></p:spPr><p:txBody><a:bodyPr wrap="square" rtlCol="0"><a:spAutoFit/></a:bodyPr><a:lstStyle/><a:p><a:r><a:rPr lang="en-US" sz="1600" dirty="0" smtClean="0"><a:latin typeface="Arial" pitchFamily="34" charset="0"/><a:cs typeface="Arial" pitchFamily="34" charset="0"/></a:rPr><a:t>Program and Dataset Flow</a:t></a:r><a:endParaRPr lang="en-US" sz="1600" dirty="0"><a:latin typeface="Arial" pitchFamily="34" charset="0"/><a:cs typeface="Arial" pitchFamily="34" charset="0"/></a:endParaRPr></a:p></p:txBody></p:sp><p:sp><p:nvSpPr><p:cNvPr id="65" name="Freeform 64"/><p:cNvSpPr/><p:nvPr/></p:nvSpPr><p:spPr><a:xfrm><a:off x="1687990" y="3336389"/><a:ext cx="1101365" cy="1030443"/></a:xfrm><a:custGeom><a:avLst/><a:gdLst><a:gd name="connsiteX0" fmla="*/ 0 w 1486621"/><a:gd name="connsiteY0" fmla="*/ 93378 h 933784"/><a:gd name="connsiteX1" fmla="*/ 27350 w 1486621"/><a:gd name="connsiteY1" fmla="*/ 27350 h 933784"/><a:gd name="connsiteX2" fmla="*/ 93378 w 1486621"/><a:gd name="connsiteY2" fmla="*/ 0 h 933784"/><a:gd name="connsiteX3" fmla="*/ 1393243 w 1486621"/><a:gd name="connsiteY3" fmla="*/ 0 h 933784"/><a:gd name="connsiteX4" fmla="*/ 1459271 w 1486621"/><a:gd name="connsiteY4" fmla="*/ 27350 h 933784"/><a:gd name="connsiteX5" fmla="*/ 1486621 w 1486621"/><a:gd name="connsiteY5" fmla="*/ 93378 h 933784"/><a:gd name="connsiteX6" fmla="*/ 1486621 w 1486621"/><a:gd name="connsiteY6" fmla="*/ 840406 h 933784"/><a:gd name="connsiteX7" fmla="*/ 1459271 w 1486621"/><a:gd name="connsiteY7" fmla="*/ 906434 h 933784"/><a:gd name="connsiteX8" fmla="*/ 1393243 w 1486621"/><a:gd name="connsiteY8" fmla="*/ 933784 h 933784"/><a:gd name="connsiteX9" fmla="*/ 93378 w 1486621"/><a:gd name="connsiteY9" fmla="*/ 933784 h 933784"/><a:gd name="connsiteX10" fmla="*/ 27350 w 1486621"/><a:gd name="connsiteY10" fmla="*/ 906434 h 933784"/><a:gd name="connsiteX11" fmla="*/ 0 w 1486621"/><a:gd name="connsiteY11" fmla="*/ 840406 h 933784"/><a:gd name="connsiteX12" fmla="*/ 0 w 1486621"/><a:gd name="connsiteY12" fmla="*/ 93378 h 933784"/></a:gdLst><a:ahLst/><a:cxnLst><a:cxn ang="0"><a:pos x="connsiteX0" y="connsiteY0"/></a:cxn><a:cxn ang="0"><a:pos x="connsiteX1" y="connsiteY1"/></a:cxn><a:cxn ang="0"><a:pos x="connsiteX2" y="connsiteY2"/></a:cxn><a:cxn ang="0"><a:pos x="connsiteX3" y="connsiteY3"/></a:cxn><a:cxn ang="0"><a:pos x="connsiteX4" y="connsiteY4"/></a:cxn><a:cxn ang="0"><a:pos x="connsiteX5" y="connsiteY5"/></a:cxn><a:cxn ang="0"><a:pos x="connsiteX6" y="connsiteY6"/></a:cxn><a:cxn ang="0"><a:pos x="connsiteX7" y="connsiteY7"/></a:cxn><a:cxn ang="0"><a:pos x="connsiteX8" y="connsiteY8"/></a:cxn><a:cxn ang="0"><a:pos x="connsiteX9" y="connsiteY9"/></a:cxn><a:cxn ang="0"><a:pos x="connsiteX10" y="connsiteY10"/></a:cxn><a:cxn ang="0"><a:pos x="connsiteX11" y="connsiteY11"/></a:cxn><a:cxn ang="0"><a:pos x="connsiteX12" y="connsiteY12"/></a:cxn></a:cxnLst><a:rect l="l" t="t" r="r" b="b"/><a:pathLst><a:path w="1486621" h="933784"><a:moveTo><a:pt x="0" y="93378"/></a:moveTo><a:cubicBezTo><a:pt x="0" y="68613"/><a:pt x="9838" y="44862"/><a:pt x="27350" y="27350"/></a:cubicBezTo><a:cubicBezTo><a:pt x="44862" y="9838"/><a:pt x="68613" y="0"/><a:pt x="93378" y="0"/></a:cubicBezTo><a:lnTo><a:pt x="1393243" y="0"/></a:lnTo><a:cubicBezTo><a:pt x="1418008" y="0"/><a:pt x="1441759" y="9838"/><a:pt x="1459271" y="27350"/></a:cubicBezTo><a:cubicBezTo><a:pt x="1476783" y="44862"/><a:pt x="1486621" y="68613"/><a:pt x="1486621" y="93378"/></a:cubicBezTo><a:lnTo><a:pt x="1486621" y="840406"/></a:lnTo><a:cubicBezTo><a:pt x="1486621" y="865171"/><a:pt x="1476783" y="888922"/><a:pt x="1459271" y="906434"/></a:cubicBezTo><a:cubicBezTo><a:pt x="1441759" y="923946"/><a:pt x="1418008" y="933784"/><a:pt x="1393243" y="933784"/></a:cubicBezTo><a:lnTo><a:pt x="93378" y="933784"/></a:lnTo><a:cubicBezTo><a:pt x="68613" y="933784"/><a:pt x="44862" y="923946"/><a:pt x="27350" y="906434"/></a:cubicBezTo><a:cubicBezTo><a:pt x="9838" y="888922"/><a:pt x="0" y="865171"/><a:pt x="0" y="840406"/></a:cubicBezTo><a:lnTo><a:pt x="0" y="93378"/></a:lnTo><a:close/></a:path></a:pathLst></a:custGeom><a:solidFill><a:srgbClr val="CCECFF"/></a:solidFill><a:ln><a:solidFill><a:srgbClr val="89A4A7"/></a:solidFill></a:ln></p:spPr><p:style><a:lnRef idx="2"><a:schemeClr val="lt1"><a:hueOff val="0"/><a:satOff val="0"/><a:lumOff val="0"/><a:alphaOff val="0"/></a:schemeClr></a:lnRef><a:fillRef idx="1"><a:scrgbClr r="0" g="0" b="0"/></a:fillRef><a:effectRef idx="0"><a:schemeClr val="accent2"><a:hueOff val="0"/><a:satOff val="0"/><a:lumOff val="0"/><a:alphaOff val="0"/></a:schemeClr></a:effectRef><a:fontRef idx="minor"><a:schemeClr val="lt1"/></a:fontRef></p:style><p:txBody><a:bodyPr spcFirstLastPara="0" vert="horz" wrap="square" lIns="95930" tIns="95930" rIns="95930" bIns="95930" numCol="1" spcCol="1270" anchor="ctr" anchorCtr="0"><a:noAutofit/></a:bodyPr><a:lstStyle/><a:p><a:pPr lvl="0" algn="ctr" defTabSz="800100"><a:lnSpc><a:spcPct val="90000"/></a:lnSpc><a:spcBef><a:spcPct val="0"/></a:spcBef><a:spcAft><a:spcPct val="35000"/></a:spcAft></a:pPr><a:r><a:rPr lang="en-US" sz="2000" dirty="0" smtClean="0"><a:solidFill><a:schemeClr val="tx1"/></a:solidFill></a:rPr><a:t>SDTM</a:t></a:r><a:endParaRPr lang="en-US" sz="2000" kern="1200" baseline="0" dirty="0" smtClean="0"><a:solidFill><a:schemeClr val="tx1"/></a:solidFill></a:endParaRPr></a:p></p:txBody></p:sp><p:sp><p:nvSpPr><p:cNvPr id="83" name="Freeform 82"/><p:cNvSpPr/><p:nvPr/></p:nvSpPr><p:spPr><a:xfrm><a:off x="6241690" y="3330725"/><a:ext cx="1366110" cy="1030443"/></a:xfrm><a:custGeom><a:avLst/><a:gdLst><a:gd name="connsiteX0" fmla="*/ 0 w 1486621"/><a:gd name="connsiteY0" fmla="*/ 93378 h 933784"/><a:gd name="connsiteX1" fmla="*/ 27350 w 1486621"/><a:gd name="connsiteY1" fmla="*/ 27350 h 933784"/><a:gd name="connsiteX2" fmla="*/ 93378 w 1486621"/><a:gd name="connsiteY2" fmla="*/ 0 h 933784"/><a:gd name="connsiteX3" fmla="*/ 1393243 w 1486621"/><a:gd name="connsiteY3" fmla="*/ 0 h 933784"/><a:gd name="connsiteX4" fmla="*/ 1459271 w 1486621"/><a:gd name="connsiteY4" fmla="*/ 27350 h 933784"/><a:gd name="connsiteX5" fmla="*/ 1486621 w 1486621"/><a:gd name="connsiteY5" fmla="*/ 93378 h 933784"/><a:gd name="connsiteX6" fmla="*/ 1486621 w 1486621"/><a:gd name="connsiteY6" fmla="*/ 840406 h 933784"/><a:gd name="connsiteX7" fmla="*/ 1459271 w 1486621"/><a:gd name="connsiteY7" fmla="*/ 906434 h 933784"/><a:gd name="connsiteX8" fmla="*/ 1393243 w 1486621"/><a:gd name="connsiteY8" fmla="*/ 933784 h 933784"/><a:gd name="connsiteX9" fmla="*/ 93378 w 1486621"/><a:gd name="connsiteY9" fmla="*/ 933784 h 933784"/><a:gd name="connsiteX10" fmla="*/ 27350 w 1486621"/><a:gd name="connsiteY10" fmla="*/ 906434 h 933784"/><a:gd name="connsiteX11" fmla="*/ 0 w 1486621"/><a:gd name="connsiteY11" fmla="*/ 840406 h 933784"/><a:gd name="connsiteX12" fmla="*/ 0 w 1486621"/><a:gd name="connsiteY12" fmla="*/ 93378 h 933784"/></a:gdLst><a:ahLst/><a:cxnLst><a:cxn ang="0"><a:pos x="connsiteX0" y="connsiteY0"/></a:cxn><a:cxn ang="0"><a:pos x="connsiteX1" y="connsiteY1"/></a:cxn><a:cxn ang="0"><a:pos x="connsiteX2" y="connsiteY2"/></a:cxn><a:cxn ang="0"><a:pos x="connsiteX3" y="connsiteY3"/></a:cxn><a:cxn ang="0"><a:pos x="connsiteX4" y="connsiteY4"/></a:cxn><a:cxn ang="0"><a:pos x="connsiteX5" y="connsiteY5"/></a:cxn><a:cxn ang="0"><a:pos x="connsiteX6" y="connsiteY6"/></a:cxn><a:cxn ang="0"><a:pos x="connsiteX7" y="connsiteY7"/></a:cxn><a:cxn ang="0"><a:pos x="connsiteX8" y="connsiteY8"/></a:cxn><a:cxn ang="0"><a:pos x="connsiteX9" y="connsiteY9"/></a:cxn><a:cxn ang="0"><a:pos x="connsiteX10" y="connsiteY10"/></a:cxn><a:cxn ang="0"><a:pos x="connsiteX11" y="connsiteY11"/></a:cxn><a:cxn ang="0"><a:pos x="connsiteX12" y="connsiteY12"/></a:cxn></a:cxnLst><a:rect l="l" t="t" r="r" b="b"/><a:pathLst><a:path w="1486621" h="933784"><a:moveTo><a:pt x="0" y="93378"/></a:moveTo><a:cubicBezTo><a:pt x="0" y="68613"/><a:pt x="9838" y="44862"/><a:pt x="27350" y="27350"/></a:cubicBezTo><a:cubicBezTo><a:pt x="44862" y="9838"/><a:pt x="68613" y="0"/><a:pt x="93378" y="0"/></a:cubicBezTo><a:lnTo><a:pt x="1393243" y="0"/></a:lnTo><a:cubicBezTo><a:pt x="1418008" y="0"/><a:pt x="1441759" y="9838"/><a:pt x="1459271" y="27350"/></a:cubicBezTo><a:cubicBezTo><a:pt x="1476783" y="44862"/><a:pt x="1486621" y="68613"/><a:pt x="1486621" y="93378"/></a:cubicBezTo><a:lnTo><a:pt x="1486621" y="840406"/></a:lnTo><a:cubicBezTo><a:pt x="1486621" y="865171"/><a:pt x="1476783" y="888922"/><a:pt x="1459271" y="906434"/></a:cubicBezTo><a:cubicBezTo><a:pt x="1441759" y="923946"/><a:pt x="1418008" y="933784"/><a:pt x="1393243" y="933784"/></a:cubicBezTo><a:lnTo><a:pt x="93378" y="933784"/></a:lnTo><a:cubicBezTo><a:pt x="68613" y="933784"/><a:pt x="44862" y="923946"/><a:pt x="27350" y="906434"/></a:cubicBezTo><a:cubicBezTo><a:pt x="9838" y="888922"/><a:pt x="0" y="865171"/><a:pt x="0" y="840406"/></a:cubicBezTo><a:lnTo><a:pt x="0" y="93378"/></a:lnTo><a:close/></a:path></a:pathLst></a:custGeom><a:solidFill><a:srgbClr val="CCECFF"/></a:solidFill><a:ln><a:solidFill><a:srgbClr val="89A4A7"/></a:solidFill></a:ln></p:spPr><p:style><a:lnRef idx="2"><a:schemeClr val="lt1"><a:hueOff val="0"/><a:satOff val="0"/><a:lumOff val="0"/><a:alphaOff val="0"/></a:schemeClr></a:lnRef><a:fillRef idx="1"><a:scrgbClr r="0" g="0" b="0"/></a:fillRef><a:effectRef idx="0"><a:schemeClr val="accent2"><a:hueOff val="0"/><a:satOff val="0"/><a:lumOff val="0"/><a:alphaOff val="0"/></a:schemeClr></a:effectRef><a:fontRef idx="minor"><a:schemeClr val="lt1"/></a:fontRef></p:style><p:txBody><a:bodyPr spcFirstLastPara="0" vert="horz" wrap="square" lIns="95930" tIns="95930" rIns="95930" bIns="95930" numCol="1" spcCol="1270" anchor="ctr" anchorCtr="0"><a:noAutofit/></a:bodyPr><a:lstStyle/><a:p><a:pPr lvl="0" algn="ctr" defTabSz="800100"><a:lnSpc><a:spcPct val="90000"/></a:lnSpc><a:spcBef><a:spcPct val="0"/></a:spcBef><a:spcAft><a:spcPct val="35000"/></a:spcAft></a:pPr><a:r><a:rPr lang="en-US" sz="1400" dirty="0" smtClean="0"><a:solidFill><a:schemeClr val="tx1"/></a:solidFill></a:rPr><a:t>Spreadsheet - 15 analyses Tables and Charts</a:t></a:r><a:endParaRPr lang="en-US" sz="1200" kern="1200" baseline="0" dirty="0" smtClean="0"><a:solidFill><a:schemeClr val="tx1"/></a:solidFill></a:endParaRPr></a:p></p:txBody></p:sp><p:sp><p:nvSpPr><p:cNvPr id="85" name="Freeform 84"/><p:cNvSpPr/><p:nvPr/></p:nvSpPr><p:spPr><a:xfrm><a:off x="2902309" y="3570128"/><a:ext cx="3339381" cy="562966"/></a:xfrm><a:custGeom><a:avLst/><a:gdLst><a:gd name="connsiteX0" fmla="*/ 0 w 559913"/><a:gd name="connsiteY0" fmla="*/ 151709 h 758545"/><a:gd name="connsiteX1" fmla="*/ 279957 w 559913"/><a:gd name="connsiteY1" fmla="*/ 151709 h 758545"/><a:gd name="connsiteX2" fmla="*/ 279957 w 559913"/><a:gd name="connsiteY2" fmla="*/ 0 h 758545"/><a:gd name="connsiteX3" fmla="*/ 559913 w 559913"/><a:gd name="connsiteY3" fmla="*/ 379273 h 758545"/><a:gd name="connsiteX4" fmla="*/ 279957 w 559913"/><a:gd name="connsiteY4" fmla="*/ 758545 h 758545"/><a:gd name="connsiteX5" fmla="*/ 279957 w 559913"/><a:gd name="connsiteY5" fmla="*/ 606836 h 758545"/><a:gd name="connsiteX6" fmla="*/ 0 w 559913"/><a:gd name="connsiteY6" fmla="*/ 606836 h 758545"/><a:gd name="connsiteX7" fmla="*/ 0 w 559913"/><a:gd name="connsiteY7" fmla="*/ 151709 h 758545"/></a:gdLst><a:ahLst/><a:cxnLst><a:cxn ang="0"><a:pos x="connsiteX0" y="connsiteY0"/></a:cxn><a:cxn ang="0"><a:pos x="connsiteX1" y="connsiteY1"/></a:cxn><a:cxn ang="0"><a:pos x="connsiteX2" y="connsiteY2"/></a:cxn><a:cxn ang="0"><a:pos x="connsiteX3" y="connsiteY3"/></a:cxn><a:cxn ang="0"><a:pos x="connsiteX4" y="connsiteY4"/></a:cxn><a:cxn ang="0"><a:pos x="connsiteX5" y="connsiteY5"/></a:cxn><a:cxn ang="0"><a:pos x="connsiteX6" y="connsiteY6"/></a:cxn><a:cxn ang="0"><a:pos x="connsiteX7" y="connsiteY7"/></a:cxn></a:cxnLst><a:rect l="l" t="t" r="r" b="b"/><a:pathLst><a:path w="559913" h="758545"><a:moveTo><a:pt x="0" y="151709"/></a:moveTo><a:lnTo><a:pt x="279957" y="151709"/></a:lnTo><a:lnTo><a:pt x="279957" y="0"/></a:lnTo><a:lnTo><a:pt x="559913" y="379273"/></a:lnTo><a:lnTo><a:pt x="279957" y="758545"/></a:lnTo><a:lnTo><a:pt x="279957" y="606836"/></a:lnTo><a:lnTo><a:pt x="0" y="606836"/></a:lnTo><a:lnTo><a:pt x="0" y="151709"/></a:lnTo><a:close/></a:path></a:pathLst></a:custGeom><a:solidFill><a:schemeClr val="accent4"><a:lumMod val="60000"/><a:lumOff val="40000"/></a:schemeClr></a:solidFill></p:spPr><p:style><a:lnRef idx="0"><a:schemeClr val="accent2"><a:tint val="60000"/><a:hueOff val="0"/><a:satOff val="0"/><a:lumOff val="0"/><a:alphaOff val="0"/></a:schemeClr></a:lnRef><a:fillRef idx="1"><a:schemeClr val="accent2"><a:tint val="60000"/><a:hueOff val="0"/><a:satOff val="0"/><a:lumOff val="0"/><a:alphaOff val="0"/></a:schemeClr></a:fillRef><a:effectRef idx="0"><a:schemeClr val="accent2"><a:tint val="60000"/><a:hueOff val="0"/><a:satOff val="0"/><a:lumOff val="0"/><a:alphaOff val="0"/></a:schemeClr></a:effectRef><a:fontRef idx="minor"><a:schemeClr val="lt1"/></a:fontRef></p:style><p:txBody><a:bodyPr spcFirstLastPara="0" vert="horz" wrap="square" lIns="0" tIns="151709" rIns="167974" bIns="151709" numCol="1" spcCol="1270" anchor="ctr" anchorCtr="0"><a:noAutofit/></a:bodyPr><a:lstStyle/><a:p><a:pPr algn="ctr" defTabSz="622300"><a:lnSpc><a:spcPct val="90000"/></a:lnSpc><a:spcBef><a:spcPct val="0"/></a:spcBef><a:spcAft><a:spcPct val="35000"/></a:spcAft></a:pPr><a:r><a:rPr lang="en-US" sz="1400" dirty="0" smtClean="0"><a:solidFill><a:schemeClr val="tx1"/></a:solidFill></a:rPr><a:t>demographics.sas</a:t></a:r><a:endParaRPr lang="en-US" sz="1050" dirty="0"><a:solidFill><a:schemeClr val="tx1"/></a:solidFill></a:endParaRPr></a:p></p:txBody></p:sp><p:sp><p:nvSpPr><p:cNvPr id="20" name="TextBox 19"/><p:cNvSpPr txBox="1"/><p:nvPr/></p:nvSpPr><p:spPr><a:xfrm><a:off x="3129995" y="5088199"/><a:ext cx="3063659" cy="769441"/></a:xfrm><a:prstGeom prst="rect"><a:avLst/></a:prstGeom><a:noFill/><a:ln><a:solidFill><a:schemeClr val="accent1"/></a:solidFill></a:ln></p:spPr><p:txBody><a:bodyPr wrap="none" rtlCol="0"><a:spAutoFit/></a:bodyPr><a:lstStyle/><a:p><a:r><a:rPr lang="en-US" sz="1100" dirty="0" smtClean="0"/><a:t>data_checks.sas -- Generic variable checks</a:t></a:r></a:p><a:p><a:r><a:rPr lang="en-US" sz="1100" dirty="0" smtClean="0"/><a:t>err_output.sas -- Error output when missing </a:t></a:r><a:r><a:rPr lang="en-US" sz="1100" dirty="0" err="1" smtClean="0"/><a:t>vars</a:t></a:r><a:endParaRPr lang="en-US" sz="1100" dirty="0" smtClean="0"/></a:p><a:p><a:r><a:rPr lang="en-US" sz="1100" dirty="0" smtClean="0"/><a:t>sl_gs_output.sas -- Script Launcher settings output</a:t></a:r></a:p><a:p><a:r><a:rPr lang="en-US" sz="1100" dirty="0" smtClean="0"/><a:t>Demographics_Template.xls -- Excel template</a:t></a:r></a:p></p:txBody></p:sp><p:cxnSp><p:nvCxnSpPr><p:cNvPr id="22" name="Straight Arrow Connector 21"/><p:cNvCxnSpPr/><p:nvPr/></p:nvCxnSpPr><p:spPr><a:xfrm><a:off x="4267810" y="4187950"/><a:ext cx="0" cy="737911"/></a:xfrm><a:prstGeom prst="straightConnector1"><a:avLst/></a:prstGeom><a:ln w="57150"><a:tailEnd type="arrow"/></a:ln></p:spPr><p:style><a:lnRef idx="1"><a:schemeClr val="accent1"/></a:lnRef><a:fillRef idx="0"><a:schemeClr val="accent1"/></a:fillRef><a:effectRef idx="0"><a:schemeClr val="accent1"/></a:effectRef><a:fontRef idx="minor"><a:schemeClr val="tx1"/></a:fontRef></p:style></p:cxnSp><p:cxnSp><p:nvCxnSpPr><p:cNvPr id="24" name="Straight Arrow Connector 23"/><p:cNvCxnSpPr/><p:nvPr/></p:nvCxnSpPr><p:spPr><a:xfrm flipV="1"><a:off x="4647895" y="4188560"/><a:ext cx="0" cy="737911"/></a:xfrm><a:prstGeom prst="straightConnector1"><a:avLst/></a:prstGeom><a:ln w="57150"><a:tailEnd type="arrow"/></a:ln></p:spPr><p:style><a:lnRef idx="1"><a:schemeClr val="accent1"/></a:lnRef><a:fillRef idx="0"><a:schemeClr val="accent1"/></a:fillRef><a:effectRef idx="0"><a:schemeClr val="accent1"/></a:effectRef><a:fontRef idx="minor"><a:schemeClr val="tx1"/></a:fontRef></p:style></p:cxnSp><p:sp><p:nvSpPr><p:cNvPr id="16" name="TextBox 15"/><p:cNvSpPr txBox="1"/><p:nvPr/></p:nvSpPr><p:spPr><a:xfrm><a:off x="1536200" y="4547839"/><a:ext cx="1418465" cy="646331"/></a:xfrm><a:prstGeom prst="rect"><a:avLst/></a:prstGeom><a:noFill/></p:spPr><p:txBody><a:bodyPr wrap="none" rtlCol="0"><a:spAutoFit/></a:bodyPr><a:lstStyle/><a:p><a:r><a:rPr lang="en-US" dirty="0" smtClean="0"/><a:t>DM.sas7bdat</a:t></a:r></a:p><a:p><a:r><a:rPr lang="en-US" dirty="0" smtClean="0"/><a:t>DS.sas7bdat</a:t></a:r><a:endParaRPr lang="en-US" dirty="0"/></a:p></p:txBody></p:sp><p:sp><p:nvSpPr><p:cNvPr id="17" name="TextBox 16"/><p:cNvSpPr txBox="1"/><p:nvPr/></p:nvSpPr><p:spPr><a:xfrm><a:off x="6014005" y="4547839"/><a:ext cx="1827808" cy="369332"/></a:xfrm><a:prstGeom prst="rect"><a:avLst/></a:prstGeom><a:noFill/></p:spPr><p:txBody><a:bodyPr wrap="none" rtlCol="0"><a:spAutoFit/></a:bodyPr><a:lstStyle/><a:p><a:r><a:rPr lang="en-US" dirty="0" smtClean="0"/><a:t>Demographics.xls</a:t></a:r><a:endParaRPr lang="en-US" dirty="0"/></a:p></p:txBody></p:sp><p:sp><p:nvSpPr><p:cNvPr id="18" name="Rectangle 17"/><p:cNvSpPr/><p:nvPr/></p:nvSpPr><p:spPr><a:xfrm><a:off x="1536200" y="3201315"/><a:ext cx="1366109" cy="3035800"/></a:xfrm><a:prstGeom prst="rect"><a:avLst/></a:prstGeom><a:noFill/><a:ln><a:solidFill><a:srgbClr val="FF0000"/></a:solidFill></a:ln></p:spPr><p:style><a:lnRef idx="2"><a:schemeClr val="accent1"><a:shade val="50000"/></a:schemeClr></a:lnRef><a:fillRef idx="1"><a:schemeClr val="accent1"/></a:fillRef><a:effectRef idx="0"><a:schemeClr val="accent1"/></a:effectRef><a:fontRef idx="minor"><a:schemeClr val="lt1"/></a:fontRef></p:style><p:txBody><a:bodyPr rtlCol="0" anchor="ctr"/><a:lstStyle/><a:p><a:pPr algn="ctr"/><a:endParaRPr lang="en-US" b="1" dirty="0" smtClean="0"><a:solidFill><a:schemeClr val="tx1"/></a:solidFill></a:endParaRPr></a:p><a:p><a:pPr algn="ctr"/><a:endParaRPr lang="en-US" b="1" dirty="0" smtClean="0"><a:solidFill><a:schemeClr val="tx1"/></a:solidFill></a:endParaRPr></a:p><a:p><a:pPr algn="ctr"/><a:endParaRPr lang="en-US" b="1" dirty="0" smtClean="0"><a:solidFill><a:schemeClr val="tx1"/></a:solidFill></a:endParaRPr></a:p><a:p><a:pPr algn="ctr"/><a:endParaRPr lang="en-US" b="1" dirty="0" smtClean="0"><a:solidFill><a:schemeClr val="tx1"/></a:solidFill></a:endParaRPr></a:p><a:p><a:pPr algn="ctr"/><a:endParaRPr lang="en-US" b="1" dirty="0" smtClean="0"><a:solidFill><a:schemeClr val="tx1"/></a:solidFill></a:endParaRPr></a:p><a:p><a:pPr algn="ctr"/><a:endParaRPr lang="en-US" b="1" dirty="0" smtClean="0"><a:solidFill><a:schemeClr val="tx1"/></a:solidFill></a:endParaRPr></a:p><a:p><a:pPr algn="ctr"/><a:endParaRPr lang="en-US" b="1" dirty="0" smtClean="0"><a:solidFill><a:schemeClr val="tx1"/></a:solidFill></a:endParaRPr></a:p><a:p><a:pPr algn="ctr"/><a:endParaRPr lang="en-US" b="1" dirty="0" smtClean="0"><a:solidFill><a:schemeClr val="tx1"/></a:solidFill></a:endParaRPr></a:p><a:p><a:pPr algn="ctr"/><a:r><a:rPr lang="en-US" b="1" dirty="0" smtClean="0"><a:solidFill><a:schemeClr val="tx1"/></a:solidFill></a:rPr><a:t>Industry Aligned</a:t></a:r><a:endParaRPr lang="en-US" b="1" dirty="0"><a:solidFill><a:schemeClr val="tx1"/></a:solidFill></a:endParaRPr></a:p></p:txBody></p:sp></p:spTree></p:cSld><p:clrMapOvr><a:masterClrMapping/></p:clrMapOvr><p:timing><p:tnLst><p:par><p:cTn id="1" dur="indefinite" restart="never" nodeType="tmRoot"/></p:par></p:tnLst></p:timing></p:sld>